{
  "$schema": "https://json-schema.org/draft/2020-12/schema",
  "$id": "ladesa://schemas/v3/generics/BlocoSetCoverImage.json",
  "type": "object",
  "properties": {
    "input": {
      "type": "object",
      "properties": {
        "params": {
          "type": "object",
          "properties": {
            "id": {
              "$ref": "ladesa://schemas/v3/generics/uuid.json",
              "description": "Identificador do registro (uuid).",
              "x-unispec-constraint-entity-exists": "Bloco"
            }
          },
          "required": ["id"]
        },
        "body": {
          "type": "string",
          "description": "Binário da imagem.",
          "mimeTypes": ["image/jpeg", "image/png", "image/jpeg", "image/webp", "binary/octet-stream"]
        }
      },
      "required": ["params", "body"]
    },
    "output": {
      "type": "object",
      "properties": {
        "success": {
          "type": "boolean",
          "description": "Resultado da operação."
        }
      },
      "required": ["success"]
    }
  },
  "required": ["input", "output"],
  "x-unispec-kind": "operation",
  "x-unispec-operation-id": "BlocoSetImagemCapa",
  "additionalProperties": false
}
